clioedb/__init__.py
clioedb/mydb.py
clioedb/mydbconn.py
clioedb/utils.py
clioedb-1.7.dist-info/LICENSE
clioedb-1.7.dist-info/METADATA
clioedb-1.7.dist-info/WHEEL
clioedb-1.7.dist-info/top_level.txt
clioedb-1.7.dist-info/RECORD
