Metadata-Version: 2.1
Name: clioedb
Version: 1.7
Summary: A module to fetch data from MySQL db as list or save it as text file
Home-page: UNKNOWN
Author: Cheny Lioe
Author-email: chenylioe@yahoo.com
License: UNKNOWN
Keywords: fetch mysql data
Platform: UNKNOWN
License-File: LICENSE
